omero/plugins/rdf.py
omero_rdf/__init__.py
omero_rdf-0.6.1.dist-info/LICENSE.txt
omero_rdf-0.6.1.dist-info/METADATA
omero_rdf-0.6.1.dist-info/WHEEL
omero_rdf-0.6.1.dist-info/top_level.txt
omero_rdf-0.6.1.dist-info/RECORD
