Metadata-Version: 2.1
Name: omero-rdf
Version: 0.6.1
Summary: A plugin for exporting RDF from OMERO
Author: The Open Microscopy Team
Project-URL: Repository, https://github.com/German-BioImaging/omero-rdf
Project-URL: Changelog, https://github.com/German-BioImaging/omero-rdf/blob/master/CHANGES.txt
Keywords: OMERO.cli,plugin
Classifier: Development Status :: 2 - Pre-Alpha
Classifier: Environment :: Plugins
Classifier: Intended Audience :: Developers
Classifier: Intended Audience :: End Users/Desktop
Classifier: License :: OSI Approved :: GNU General Public License v2 or later (GPLv2+)
Classifier: Natural Language :: English
Classifier: Operating System :: OS Independent
Classifier: Programming Language :: Python :: 3
Classifier: Topic :: Software Development :: Libraries :: Python Modules
Requires-Python: >3.8
License-File: LICENSE.txt
Requires-Dist: omero-py>=5.8
Requires-Dist: importlib-metadata
Requires-Dist: future
Requires-Dist: rdflib
Requires-Dist: pyld
Requires-Dist: rdflib-pyld-compat
Requires-Dist: omero-marshal
Requires-Dist: packaging
Provides-Extra: tests
Requires-Dist: pytest; extra == "tests"
Requires-Dist: restview; extra == "tests"
Requires-Dist: mox3; extra == "tests"
